[
   {
        "id":"0",
        "Website":"HackkerRank", 
        "level":"beginner",
        "interview_preparations":"Begineer",
        "website_link":"https://www.hackerrank.com/dashboard"
         
    },
{
        "id":"1",
        "Website":"HackerEarth",
        "level":"Beginner",
        "interview_preparations":"advance",
      "website_link":"https://www.hackerearth.com/for-developers"
    },
{
        "id":"3",
        "Website":"Codeforces", 
        "level":"advance",
        "interview_preparations":"",
        "Website" : "https://codeforces.com/",
        "website_link":"http://codeforces.com/"
    },
    {
        "id":"4",
        "Website":"Exercism", 
        "level":"beginner",
        "interview_preparations":"",
        "website_link":"https://exercism.org/"
    },
    {
        "id":"5",
        "Website":"Leetcode", 
        "level":"beginner",
        "interview_preparations":"",
        "website_link":"https://leetcode.com/"
    },
    {
        "id":"6",
        "Website":"Codechef", 
        "level":"advance",
        "interview_preparations":"advance",
        "website_link":"https://www.codechef.com/",
    },
    }
        "id":"7",
        "Website":"Codeacademy", 
        "level":"beginner",
        "interview_preparations":"",
        "website_link":"https://www.codecademy.com/",
    }
  ]
